Metadata-Version: 2.1
Name: odoo14-addon-pricelist_cache
Version: 14.0.1.6.0
Summary: Provide a new model to cache price lists and update it, to make it easier to retrieve them.
Home-page: https://github.com/OCA/sale-workflow
Author: Camptocamp, Odoo Community Association (OCA)
Author-email: support@odoo-community.org
License: AGPL-3
Classifier: Programming Language :: Python
Classifier: Framework :: Odoo
Classifier: Framework :: Odoo :: 14.0
Classifier: License :: OSI Approved :: GNU Affero General Public License v3
Requires-Python: >=3.6
Requires-Dist: odoo14-addon-partner-pricelist-search
Requires-Dist: odoo14-addon-queue-job
Requires-Dist: odoo<14.1dev,>=14.0a
